microsoft/__init__.py
microsoft/bing/__init__.py
microsoft/bing/commerce/__init__.py
microsoft/bing/commerce/ingestion/__init__.py
microsoft/bing/commerce/ingestion/bing_commerce_ingestion.py
microsoft/bing/commerce/ingestion/version.py
microsoft/bing/commerce/ingestion/models/__init__.py
microsoft/bing/commerce/ingestion/models/bing_commerce_ingestion_enums.py
microsoft/bing/commerce/ingestion/models/delete_documents_response.py
microsoft/bing/commerce/ingestion/models/delete_documents_response_py3.py
microsoft/bing/commerce/ingestion/models/index.py
microsoft/bing/commerce/ingestion/models/index_field.py
microsoft/bing/commerce/ingestion/models/index_field_py3.py
microsoft/bing/commerce/ingestion/models/index_py3.py
microsoft/bing/commerce/ingestion/models/index_response.py
microsoft/bing/commerce/ingestion/models/index_response_py3.py
microsoft/bing/commerce/ingestion/models/index_status_response.py
microsoft/bing/commerce/ingestion/models/index_status_response_py3.py
microsoft/bing/commerce/ingestion/models/push_data_update_response.py
microsoft/bing/commerce/ingestion/models/push_data_update_response_py3.py
microsoft/bing/commerce/ingestion/models/push_update_status_response.py
microsoft/bing/commerce/ingestion/models/push_update_status_response_py3.py
microsoft/bing/commerce/ingestion/models/requests_string_set.py
microsoft/bing/commerce/ingestion/models/requests_string_set_py3.py
microsoft/bing/commerce/ingestion/models/response_document_deletion_result.py
microsoft/bing/commerce/ingestion/models/response_document_deletion_result_py3.py
microsoft/bing/commerce/ingestion/models/response_index.py
microsoft/bing/commerce/ingestion/models/response_index_py3.py
microsoft/bing/commerce/ingestion/models/response_index_status.py
microsoft/bing/commerce/ingestion/models/response_index_status_py3.py
microsoft/bing/commerce/ingestion/models/response_record_status.py
microsoft/bing/commerce/ingestion/models/response_record_status_py3.py
bing_commerce_ingestion-1.dist-info/METADATA
bing_commerce_ingestion-1.dist-info/WHEEL
bing_commerce_ingestion-1.dist-info/top_level.txt
bing_commerce_ingestion-1.dist-info/RECORD
