Metadata-Version: 2.1
Name: bing-commerce-ingestion
Version: 1
Summary: Microsoft Bing for Commerce ingestion SDK for Python
Home-page: https://github.com/Azure/azure-sdk-for-python
Author: Microsoft Corporation
Author-email: opencommerce@microsoft.com
Maintainer: Microsoft
Maintainer-email: opencommerce@microsoft.com
License: MIT License
Platform: UNKNOWN
Classifier: Development Status :: 4 - Beta
Classifier: Intended Audience :: Developers
Classifier: Natural Language :: English
Classifier: Operating System :: OS Independent
Classifier: Programming Language :: Python
Classifier: Programming Language :: Python :: 2
Classifier: Programming Language :: Python :: 2.7
Classifier: Programming Language :: Python :: 3
Classifier: Programming Language :: Python :: 3.5
Classifier: Programming Language :: Python :: 3.6
Classifier: Programming Language :: Python :: 3.7
Classifier: Programming Language :: Python :: 3.8
Classifier: Topic :: Internet :: WWW/HTTP :: Indexing/Search
Classifier: License :: OSI Approved :: MIT License
Requires-Dist: certifi (==2019.9.11)
Requires-Dist: chardet (==3.0.4)
Requires-Dist: enum34 (==1.1.6)
Requires-Dist: idna (==2.8)
Requires-Dist: isodate (==0.6.0)
Requires-Dist: msrest (==0.6.10)
Requires-Dist: oauthlib (==3.1.0)
Requires-Dist: requests (==2.22.0)
Requires-Dist: requests-oauthlib (==1.2.0)
Requires-Dist: six (==1.12.0)
Requires-Dist: typing (==3.7.4.1)
Requires-Dist: urllib3 (==1.25.6)
